password_expire/__init__.py
password_expire/apps.py
password_expire/middleware.py
password_expire/model.py
password_expire/signals.py
password_expire/util.py
password_expire/migrations/0001_initial.py
password_expire/migrations/__init__.py
password_expire/tests/__init__.py
password_expire/tests/settings.py
password_expire/tests/test_util.py
django_password_expire-0.2.dist-info/LICENSE
django_password_expire-0.2.dist-info/METADATA
django_password_expire-0.2.dist-info/WHEEL
django_password_expire-0.2.dist-info/top_level.txt
django_password_expire-0.2.dist-info/RECORD
