Metadata-Version: 2.1
Name: django-password-expire
Version: 0.2
Summary: Django app for forcing password expiration
Home-page: https://github.com/cash/django-password-expire
Author: Cash Costello
Author-email: cash.costello@gmail.com
License: BSD
Classifier: Development Status :: 5 - Production/Stable
Classifier: Environment :: Web Environment
Classifier: Intended Audience :: Developers
Classifier: License :: OSI Approved :: BSD License
Classifier: Programming Language :: Python :: 3
Classifier: Framework :: Django
Requires-Python: >=3.6
License-File: LICENSE
